echoss_db/__init__.py
echoss_db/elastic_search.py
echoss_db/mongo_query.py
echoss_db/mysql_query.py
echoss_db-1.2.2.dist-info/METADATA
echoss_db-1.2.2.dist-info/WHEEL
echoss_db-1.2.2.dist-info/top_level.txt
echoss_db-1.2.2.dist-info/RECORD
