Metadata-Version: 2.4
Name: echoss-db
Version: 1.2.2
Summary: echoss AI Bigdata Solution - Database Query Package
Home-page: https://github.com/12cmlab/echoss-query
Author: ckkim
Author-email: ckkim@12cm.co.kr
License: Apache License 2.0
Classifier: Programming Language :: Python :: 3
Classifier: Operating System :: OS Independent
Requires-Python: >3.7
Requires-Dist: pandas>=1.5.3
Requires-Dist: pymongo>=4.3.3
Requires-Dist: sqlalchemy>=2.0.0
Requires-Dist: PyMySQL>=1.0.2
Requires-Dist: PyYAML>=6.0
Requires-Dist: opensearch-py>=2.2.0
Requires-Dist: echoss-fileformat>=1.1.2
Dynamic: author
Dynamic: author-email
Dynamic: classifier
Dynamic: description
Dynamic: description-content-type
Dynamic: home-page
Dynamic: license
Dynamic: requires-dist
Dynamic: requires-python
Dynamic: summary
